[{"posX":499,"posY":228,"posW":150,"posH":16,"color":"yellow","title":"BUS"},{"posX":499,"posY":208,"posW":150,"posH":16,"color":"red","title":"BUS"},{"posX":309,"posY":293,"posW":200,"posH":16,"color":"green","title":"985N"},{"posX":309,"posY":313,"posW":200,"posH":16,"color":"green","title":"985N"},{"posX":659,"posY":293,"posW":140,"posH":16,"color":"green","title":"GSN"},{"posX":659,"posY":313,"posW":140,"posH":16,"color":"green","title":"GSN"},{"posX":140,"posY":293,"posW":160,"posH":16,"color":"green","title":"MGN"},{"posX":140,"posY":313,"posW":160,"posH":16,"color":"green","title":"MGN"},{"posX":659,"posY":228,"posW":190,"posH":16,"color":"green","title":"GSS"},{"posX":659,"posY":208,"posW":190,"posH":16,"color":"green","title":"GSS"},{"posX":309,"posY":228,"posW":180,"posH":16,"color":"green","title":"985S"},{"posX":309,"posY":208,"posW":180,"posH":16,"color":"green","title":"985S"},{"posX":140,"posY":228,"posW":160,"posH":16,"color":"green","title":"MGS"},{"posX":140,"posY":208,"posW":160,"posH":16,"color":"green","title":"MGS"},{"posX":519,"posY":293,"posW":130,"posH":16,"color":"green","title":"BUN"},{"posX":519,"posY":313,"posW":130,"posH":16,"color":"red","title":"BUN"}]